alr_spec/__init__.py
alr_spec/__main__.py
alr_spec/main.py
alr_spec/commands/build.py
alr_spec/commands/checksums.py
alr_spec/commands/create.py
alr_spec/commands/field.py
alr_spec/commands/update.py
alr_spec/core/checksums.py
alr_spec/core/field_ops.py
alr_spec/core/replacer_factory.py
alr_spec/core/update.py
alr_spec/core/utils.py
alr_spec/replacers/__init__.py
alr_spec/replacers/arch_replacer.py
alr_spec/replacers/base.py
alr_spec/replacers/simple_replacer.py
alr_spec/replacers/sources.py
alr_spec/replacers/sources_replacer.py
alr_spec/utils/empty_template.py
alr_spec/utils/from_pkgbuild.py
alr_spec-0.0.5.dist-info/METADATA
alr_spec-0.0.5.dist-info/WHEEL
alr_spec-0.0.5.dist-info/entry_points.txt
alr_spec-0.0.5.dist-info/RECORD
