Metadata-Version: 2.4
Name: alr-spec
Version: 0.0.5
Summary: Experimental CLI helper for ALR
Author-email: Maxim Slipenko <maks1ms@alt-gnome.ru>
Requires-Python: ~=3.12
Requires-Dist: gitpython<4,>=3.1.44
Requires-Dist: requests<3,>=2.32.3
Requires-Dist: tree-sitter-bash<0.24,>=0.23.3
Requires-Dist: tree-sitter<0.25,>=0.24.0
Requires-Dist: typer<0.16,>=0.15.1
